bug_trail_core/__about__.py
bug_trail_core/__init__.py
bug_trail_core/__main__.py
bug_trail_core/config.py
bug_trail_core/create_table.sql
bug_trail_core/exceptions.py
bug_trail_core/generate_sql.py
bug_trail_core/handlers.py
bug_trail_core/py.typed
bug_trail_core/report_meta.py
bug_trail_core/sqlite3_utils.py
bug_trail_core/system_info.py
bug_trail_core/venv_info.py
bug_trail_core-3.1.0.dist-info/METADATA
bug_trail_core-3.1.0.dist-info/WHEEL
bug_trail_core-3.1.0.dist-info/entry_points.txt
bug_trail_core-3.1.0.dist-info/licenses/AUTHORS
bug_trail_core-3.1.0.dist-info/licenses/LICENSE
bug_trail_core-3.1.0.dist-info/RECORD
