Metadata-Version: 2.4
Name: bug_trail_core
Version: 3.1.0
Summary: Local static html error logger to use while developing python code.
Project-URL: Bug Tracker, https://github.com/matthewdeanmartin/bug_trail_core/issues
Project-URL: Change Log, https://github.com/matthewdeanmartin/bug_trail_core/blob/main/CHANGES.md
Author-email: Matthew Martin <matthewdeanmartin@gmail.com>
License: MIT
License-File: AUTHORS
License-File: LICENSE
Keywords: error logging,html log report
Classifier: Development Status :: 4 - Beta
Classifier: Intended Audience :: Developers
Classifier: License :: OSI Approved :: MIT License
Classifier: Operating System :: OS Independent
Classifier: Programming Language :: Python
Classifier: Programming Language :: Python :: 3.11
Classifier: Programming Language :: Python :: 3.12
Classifier: Programming Language :: Python :: 3.13
Requires-Python: >=3.9
Requires-Dist: platformdirs
Requires-Dist: psutil
